continouous_stock_adjustment/__init__.py
continouous_stock_adjustment/api_test.py
continouous_stock_adjustment/core.py
continouous_stock_adjustment/serializers.py
continouous_stock_adjustment/views.py
continouous_stock_adjustment/static/Dashboard.js
continouous_stock_adjustment/static/Panel.js
continouous_stock_adjustment/static/Settings.js
continouous_stock_adjustment/static/StockRemovalPage.js
continouous_stock_adjustment/static/.vite/manifest.json
continouous_stock_adjustment/static/assets/RowActions-5NS1uw9x.js
inventree_continouous_stock_adjustment-0.2.3.dist-info/licenses/LICENSE
inventree_continouous_stock_adjustment-0.2.3.dist-info/METADATA
inventree_continouous_stock_adjustment-0.2.3.dist-info/WHEEL
inventree_continouous_stock_adjustment-0.2.3.dist-info/entry_points.txt
inventree_continouous_stock_adjustment-0.2.3.dist-info/top_level.txt
inventree_continouous_stock_adjustment-0.2.3.dist-info/RECORD
