Metadata-Version: 2.4
Name: inventree-continouous-stock-adjustment
Version: 0.2.3
Summary: Perform quick and intuitive stock adjustments by scanning barcodes to remove articles from stock
Author-email: Daniel Schwab <daniel.schwab@hadiko.de>
License-Expression: MIT
Keywords: inventree,plugin
Classifier: Programming Language :: Python :: 3
Classifier: Operating System :: OS Independent
Classifier: Framework :: InvenTree
Requires-Python: >=3.9
License-File: LICENSE
Dynamic: license-file
